Workbook

Sheet Assumptions
B2: VerifIQ — Financial Model
B3: Solo-reviewer phase · VerifIQ inside GovIQ Ltd · Ireland launch
B4: v0.1 · 2026-06-01 · Liam Doolan
B6: Frame
B7: VerifIQ ships as a product line inside GovIQ Ltd. Only incremental cash is modelled here. Solo reviewer phase (founder signs within discipline) avoids panel honoraria until trigger fires. Five tiers; early-pilot 30% off first ten practices.
B9: Color conventions
B10: Inputs (change for scenarios)
B11: Calculations / formulas
B12: Cross-sheet references
B13: Key assumption — review
B15: Core Inputs
B16: Parameter | C16: Value | D16: Unit | E16: Notes
B17: Tier I — Small price (per pack) | C17: 290 | D17: € | E17: Doc 14 launch pricing
B18: Tier II — Mid price (per pack) | C18: 590 | D18: €
B19: Tier III — Large price (per pack) | C19: 890 | D19: € | E19: Featured tier
B20: Tier IV — Programme (per pack) | C20: 1950 | D20: €
B21: Tier V — Mega (per pack) | C21: 2500 | D21: € | E21: From; by arrangement
B22: Tier I — Annual seat | C22: 2800 | D22: €
B23: Tier II — Annual seat | C23: 5800 | D23: €
B24: Tier III — Annual seat | C24: 11400 | D24: €
B25: Tier IV — Annual seat | C25: 19800 | D25: €
B26: Tier V — Annual seat | C26: 36000 | D26: € | E26: From
B27: Early-pilot discount (first 10) | C27: 0.3 | D27: % | E27: YELLOW — review at month 4
B28: Free taster compute cost (per scan) | C28: 3.5 | D28: € | E28: Skim only (Haiku)
B29: Paid scan compute cost — Tier III | C29: 28 | D29: € | E29: Sonnet + verify + coordination
B30: Anthropic + OpenAI markup applied | C30: 0.15 | D30: % | E30: Cost buffer
B31: Per-pack specialist honorarium (Option C) | C31: 250 | D31: € | E31: When Option C invoked; not every pack
B32: Reviewer chair retention (one-off, when triggered) | C32: 1500 | D32: € | E32: Triggered by 4 packs/wk × 4 weeks or dispute
B33: Solicitor — Phase 2 legal pack | C33: 2500 | D33: € | E33: TOS + Privacy + DPA + rider review
B34: Tech E&O rider — annual | C34: 1000 | D34: € | E34: Monthly-paid; rider on GovIQ policy
B35: Trademark IE filing (triggered at €5k revenue) | C35: 500 | D35: €
B36: Domain + email + ancillary infra (yr 1) | C36: 200 | D36: €
B37: Free-tier compute weekly cap | C37: 1500 | D37: € | E37: Hard cap from Doc 11
B38: Free → demo conversion | C38: 0.4 | D38: % | E38: Doc 19
B39: Demo → paid pilot conversion | C39: 0.3 | D39: % | E39: Doc 19
B40: VAT rate (Ireland) | C40: 0.23 | D40: % | E40: B2B reverse-charge for non-IE EU; not in revenue figures

Sheet Monthly Cashflow Y1
B2: Monthly Cashflow — Year 1 (2026-06 → 2027-05)
B3: VerifIQ-incremental only. All figures €.
B6: Line | C6: M01 | D6: M02 | E6: M03 | F6: M04 | G6: M05 | H6: M06 | I6: M07 | J6: M08 | K6: M09 | L6: M10 | M6: M11 | N6: M12 | O6: Year 1
B7: Month label | C7: Jun-26 | D7: Jul-26 | E7: Aug-26 | F7: Sep-26 | G7: Oct-26 | H7: Nov-26 | I7: Dec-26 | J7: Jan-27 | K7: Feb-27 | L7: Mar-27 | M7: Apr-27 | N7: May-27
B9: REVENUE — paid scans
B10: New paying customers (input) | C10: 0 | D10: 0 | E10: 1 | F10: 1 | G10: 1 | H10: 1 | I10: 1 | J10: 2 | K10: 2 | L10: 2 | M10: 2 | N10: 2 | O10: =SUM(C10:N10) -> 15
B11: Cumulative paying customers | C11: =C10 -> 0 | D11: =C11+D10 -> 0 | E11: =D11+E10 -> 1 | F11: =E11+F10 -> 2 | G11: =F11+G10 -> 3 | H11: =G11+H10 -> 4 | I11: =H11+I10 -> 5 | J11: =I11+J10 -> 7 | K11: =J11+K10 -> 9 | ... N11: =M11+N10 -> 15 | O11: =N11 -> 15
B13: Tier mix on new customers (input)
B14: Tier I share | C14: 0.3 | D14: 0.3 | E14: 0.3 | F14: 0.3 | G14: 0.3 | H14: 0.3 | I14: 0.3 | J14: 0.3 | K14: 0.3 | L14: 0.3 | M14: 0.3 | N14: 0.3
B15: Tier II share | C15: 0.4 | D15: 0.4 | E15: 0.4 | F15: 0.4 | G15: 0.4 | H15: 0.4 | I15: 0.4 | J15: 0.4 | K15: 0.4 | L15: 0.4 | M15: 0.4 | N15: 0.4
B16: Tier III share | C16: 0.3 | D16: 0.3 | E16: 0.3 | F16: 0.3 | G16: 0.3 | H16: 0.3 | I16: 0.3 | J16: 0.3 | K16: 0.3 | L16: 0.3 | M16: 0.3 | N16: 0.3
B18: Avg packs per customer per month | C18: 0.4 | D18: 0.4 | E18: 0.4 | F18: 0.4 | G18: 0.4 | H18: 0.4 | I18: 0.4 | J18: 0.4 | K18: 0.4 | L18: 0.4 | M18: 0.4 | N18: 0.4
B20: Pack revenue (gross of early-pilot disc.) | C20: =C11*C18*(C14*Assumptions!$C$17+C15*Assumptions!$C$18+C16*Assumptions!$C$19) -> 0 | D20: =D11*D18*(D14*Assumptions!$C$17+D15*Assumptions!$C$18+D16*Assumptions!$C$19) -> 0 | E20: =E11*E18*(E14*Assumptions!$C$17+E15*Assumptions!$C$18+E16*Assumptions!$C$19) -> 236 | F20: =F11*F18*(F14*Assumptions!$C$17+F15*Assumptions!$C$18+F16*Assumptions!$C$19) -> 472 | G20: =G11*G18*(G14*Assumptions!$C$17+G15*Assumptions!$C$18+G16*Assumptions!$C$19) -> 708 | H20: =H11*H18*(H14*Assumptions!$C$17+H15*Assumptions!$C$18+H16*Assumptions!$C$19) -> 944 | I20: =I11*I18*(I14*Assumptions!$C$17+I15*Assumptions!$C$18+I16*Assumptions!$C$19) -> 1180 | J20: =J11*J18*(J14*Assumptions!$C$17+J15*Assumptions!$C$18+J16*Assumptions!$C$19) -> 1652 | ... N20: =N11*N18*(N14*Assumptions!$C$17+N15*Assumptions!$C$18+N16*Assumptions!$C$19) -> 3540 | O20: =SUM(C20:N20) -> 16520
B21: Less: early-pilot 30% (first 10 customers) | C21: =-IF(C11<=10,C20*Assumptions!$C$25,C20*Assumptions!$C$25*10/C11) -> 0 | D21: =-IF(D11<=10,D20*Assumptions!$C$25,D20*Assumptions!$C$25*10/D11) -> 0 | E21: =-IF(E11<=10,E20*Assumptions!$C$25,E20*Assumptions!$C$25*10/E11) -> -4672800 | F21: =-IF(F11<=10,F20*Assumptions!$C$25,F20*Assumptions!$C$25*10/F11) -> -9345600 | G21: =-IF(G11<=10,G20*Assumptions!$C$25,G20*Assumptions!$C$25*10/G11) -> -14018400 | H21: =-IF(H11<=10,H20*Assumptions!$C$25,H20*Assumptions!$C$25*10/H11) -> -18691200 | I21: =-IF(I11<=10,I20*Assumptions!$C$25,I20*Assumptions!$C$25*10/I11) -> -23364000 | J21: =-IF(J11<=10,J20*Assumptions!$C$25,J20*Assumptions!$C$25*10/J11) -> -32709600 | ... N21: =-IF(N11<=10,N20*Assumptions!$C$25,N20*Assumptions!$C$25*10/N11) -> -46728000 | O21: =SUM(C21:N21) -> -285040800
B22: NET REVENUE | C22: =C20+C21 -> 0 | D22: =D20+D21 -> 0 | E22: =E20+E21 -> -4672564 | F22: =F20+F21 -> -9345128 | G22: =G20+G21 -> -14017692 | H22: =H20+H21 -> -18690256 | I22: =I20+I21 -> -23362820 | J22: =J20+J21 -> -32707948 | ... N22: =N20+N21 -> -46724460 | O22: =SUM(C22:N22) -> -285024280
B24: DIRECT COSTS
B25: Paid scan compute cost | C25: =-C11*C18*Assumptions!$C$28*(1+Assumptions!$C$29) -> 0 | D25: =-D11*D18*Assumptions!$C$28*(1+Assumptions!$C$29) -> 0 | E25: =-E11*E18*Assumptions!$C$28*(1+Assumptions!$C$29) -> -40.6 | F25: =-F11*F18*Assumptions!$C$28*(1+Assumptions!$C$29) -> -81.2 | G25: =-G11*G18*Assumptions!$C$28*(1+Assumptions!$C$29) -> -121.8 | H25: =-H11*H18*Assumptions!$C$28*(1+Assumptions!$C$29) -> -162.4 | I25: =-I11*I18*Assumptions!$C$28*(1+Assumptions!$C$29) -> -203 | J25: =-J11*J18*Assumptions!$C$28*(1+Assumptions!$C$29) -> -284.2 | ... N25: =-N11*N18*Assumptions!$C$28*(1+Assumptions!$C$29) -> -609 | O25: =SUM(C25:N25) -> -2842
B26: Free taster compute (estimated 15-50/mo) | C26: =-5*Assumptions!$C$27 -> -1.5 | D26: =-10*Assumptions!$C$27 -> -3 | E26: =-15*Assumptions!$C$27 -> -4.5 | F26: =-20*Assumptions!$C$27 -> -6 | G26: =-25*Assumptions!$C$27 -> -7.5 | H26: =-30*Assumptions!$C$27 -> -9 | I26: =-30*Assumptions!$C$27 -> -9 | J26: =-35*Assumptions!$C$27 -> -10.5 | K26: =-40*Assumptions!$C$27 -> -12 | L26: =-40*Assumptions!$C$27 -> -12 | M26: =-45*Assumptions!$C$27 -> -13.5 | N26: =-50*Assumptions!$C$27 -> -15 | O26: =SUM(C26:N26) -> -103.5
B27: Per-pack specialist honorarium (Option C) | C27: =-0*Assumptions!$C$30 -> 0 | D27: =-0*Assumptions!$C$30 -> 0 | E27: =-0*Assumptions!$C$30 -> 0 | F27: =-0*Assumptions!$C$30 -> 0 | G27: =-0*Assumptions!$C$30 -> 0 | H27: =-1*Assumptions!$C$30 -> -0.15 | I27: =-1*Assumptions!$C$30 -> -0.15 | J27: =-2*Assumptions!$C$30 -> -0.3 | K27: =-2*Assumptions!$C$30 -> -0.3 | L27: =-2*Assumptions!$C$30 -> -0.3 | M27: =-3*Assumptions!$C$30 -> -0.45 | N27: =-3*Assumptions!$C$30 -> -0.45 | O27: =SUM(C27:N27) -> -2.1
B28: TOTAL DIRECT COSTS | C28: =SUM(C25:C27) -> -1.5 | D28: =SUM(D25:D27) -> -3 | E28: =SUM(E25:E27) -> -45.1 | F28: =SUM(F25:F27) -> -87.2 | G28: =SUM(G25:G27) -> -129.3 | H28: =SUM(H25:H27) -> -171.55 | I28: =SUM(I25:I27) -> -212.15 | J28: =SUM(J25:J27) -> -295 | ... N28: =SUM(N25:N27) -> -624.45 | O28: =SUM(C28:N28) -> -2947.6
B29: GROSS MARGIN | C29: =C22+C28 -> -1.5 | D29: =D22+D28 -> -3 | E29: =E22+E28 -> -4672609.1 | F29: =F22+F28 -> -9345215.2 | G29: =G22+G28 -> -14017821 | H29: =H22+H28 -> -18690428 | I29: =I22+I28 -> -23363032 | J29: =J22+J28 -> -32708243 | ... N29: =N22+N28 -> -46725084 | O29: =SUM(C29:N29) -> -2.8502723e+08
B31: OPERATING EXPENSES — VerifIQ-incremental
B32: Domain + infra setup (one-off) | C32: -200 | D32: 0 | E32: 0 | F32: 0 | G32: 0 | H32: 0 | I32: 0 | J32: 0 | K32: 0 | L32: 0 | M32: 0 | N32: 0 | O32: =SUM(C32:N32) -> -200
B33: Solicitor — Phase 2 legal pack | C33: 0 | D33: -2500 | E33: 0 | F33: 0 | G33: 0 | H33: 0 | I33: 0 | J33: 0 | K33: 0 | L33: 0 | M33: 0 | N33: 0 | O33: =SUM(C33:N33) -> -2500
B34: Tech E&O rider (monthly) | C34: 0 | D34: -83.333333 | E34: -83.333333 | F34: -83.333333 | G34: -83.333333 | H34: -83.333333 | I34: -83.333333 | J34: -83.333333 | K34: -83.333333 | L34: -83.333333 | M34: -83.333333 | N34: -83.333333 | O34: =SUM(C34:N34) -> -916.66667
B35: Panel chair retention (triggered m6) | C35: 0 | D35: 0 | E35: 0 | F35: 0 | G35: 0 | H35: -1500 | I35: 0 | J35: 0 | K35: 0 | L35: 0 | M35: 0 | N35: 0 | O35: =SUM(C35:N35) -> -1500
B36: Case study artefact (m3) | C36: 0 | D36: 0 | E36: -3000 | F36: 0 | G36: 0 | H36: 0 | I36: 0 | J36: 0 | K36: 0 | L36: 0 | M36: 0 | N36: 0 | O36: =SUM(C36:N36) -> -3000
B37: Trademark IE filing (m6) | C37: 0 | D37: 0 | E37: 0 | F37: 0 | G37: 0 | H37: -500 | I37: 0 | J37: 0 | K37: 0 | L37: 0 | M37: 0 | N37: 0 | O37: =SUM(C37:N37) -> -500
B38: Conferences — RIAI / EI (m4, m10) | C38: 0 | D38: 0 | E38: 0 | F38: -900 | G38: 0 | H38: 0 | I38: 0 | J38: 0 | K38: 0 | L38: -900 | M38: 0 | N38: 0 | O38: =SUM(C38:N38) -> -1800
B39: Marketing (LinkedIn / content) | C39: 0 | D39: -150 | E39: -150 | F39: -150 | G39: -150 | H39: -150 | I39: -150 | J39: -150 | K39: -150 | L39: -150 | M39: -150 | N39: -150 | O39: =SUM(C39:N39) -> -1650
B40: TOTAL OPEX | C40: =SUM(C32:C39) -> -200 | D40: =SUM(D32:D39) -> -2733.3333 | E40: =SUM(E32:E39) -> -3233.3333 | F40: =SUM(F32:F39) -> -1133.3333 | G40: =SUM(G32:G39) -> -233.33333 | H40: =SUM(H32:H39) -> -2233.3333 | I40: =SUM(I32:I39) -> -233.33333 | J40: =SUM(J32:J39) -> -233.33333 | ... N40: =SUM(N32:N39) -> -233.33333 | O40: =SUM(C40:N40) -> -12066.667
B42: NET CASH CONTRIBUTION (Pre-Founder) | C42: =C29+C40 -> -201.5 | D42: =D29+D40 -> -2736.3333 | E42: =E29+E40 -> -4675842.4 | F42: =F29+F40 -> -9346348.5 | G42: =G29+G40 -> -14018055 | H42: =H29+H40 -> -18692661 | I42: =I29+I40 -> -23363265 | J42: =J29+J40 -> -32708476 | ... N42: =N29+N40 -> -46725318 | O42: =SUM(C42:N42) -> -2.8503929e+08
B44: Cumulative net cash (VerifIQ-incremental) | C44: =C42 -> -201.5 | D44: =C44+D42 -> -2937.8333 | E44: =D44+E42 -> -4678780.3 | F44: =E44+F42 -> -14025129 | G44: =F44+G42 -> -28043183 | H44: =G44+H42 -> -46735844 | I44: =H44+I42 -> -70099110 | J44: =I44+J42 -> -1.0280759e+08 | K44: =J44+K42 -> -1.4486127e+08 | ... N44: =M44+N42 -> -2.8503929e+08 | O44: =N44 -> -2.8503929e+08
B47: Notes
B48: • Founder salary excluded — taken from GovIQ parent operations as cost-shared.
B49: • Annual seat revenue not yet modelled — defer to Year 2-3 sheet (typically signs from month 6 onwards).
B50: • VAT excluded throughout — net of VAT figures shown.
B51: • Conservative customer ramp: 15 paying customers in year 1 (vs Doc 14 credible-case of 8-15).
B52: • Solo-reviewer phase ends when 4 packs/wk × 4 weeks sustained — modelled at m6 with panel chair trigger.
B53: • Free taster compute cap of €1,500/wk is not breached at modelled volumes (50/mo max = €175).

Sheet Tier Economics
B2: Tier Economics — Per-pack contribution
B3: Unit margin per tier at list price and at early-pilot 30% off.
C6: Tier I | D6: Tier II | E6: Tier III | F6: Tier IV | G6: Tier V
B7: List price (per pack) | C7: =Assumptions!C17 -> 290 | D7: =Assumptions!C18 -> 590 | E7: =Assumptions!C19 -> 890 | F7: =Assumptions!C20 -> 1950 | G7: =Assumptions!C21 -> 2500
B8: Early-pilot (30% off) | C8: =C7*(1-Assumptions!$C$25) -> -5741710 | D8: =D7*(1-Assumptions!$C$25) -> -11681410 | E8: =E7*(1-Assumptions!$C$25) -> -17621110 | F8: =F7*(1-Assumptions!$C$25) -> -38608050 | G8: =G7*(1-Assumptions!$C$25) -> -49497500
B10: Compute cost | C10: 8 | D10: 18 | E10: 28 | F10: 60 | G10: 120
B11: Specialist honorarium | C11: =0.05*Assumptions!$C$30 -> 0.0075 | D11: =0.15*Assumptions!$C$30 -> 0.0225 | E11: =0.3*Assumptions!$C$30 -> 0.045 | F11: =0.4*Assumptions!$C$30 -> 0.06 | G11: =0.5*Assumptions!$C$30 -> 0.075
B12: Reviewer time (hrs) | C12: 1.5 | D12: 3 | E12: 6 | F12: 12 | G12: 24
B14: Unit contribution (list) | C14: =C7-C10-C11 -> 281.9925 | D14: =D7-D10-D11 -> 571.9775 | E14: =E7-E10-E11 -> 861.955 | F14: =F7-F10-F11 -> 1889.94 | G14: =G7-G10-G11 -> 2379.925
B15: Unit contribution (early-pilot) | C15: =C8-C10-C11 -> -5741718 | D15: =D8-D10-D11 -> -11681428 | E15: =E8-E10-E11 -> -17621138 | F15: =F8-F10-F11 -> -38608110 | G15: =G8-G10-G11 -> -49497620
B16: Gross margin % (list) | C16: =C14/C7 -> 0.97238793 | D16: =D14/D7 -> 0.96945339 | E16: =E14/E7 -> 0.96848876 | F16: =F14/F7 -> 0.9692 | G16: =G14/G7 -> 0.95197
B19: ANNUAL SEAT
B20: Annual seat price | C20: =Assumptions!C22 -> 2800 | D20: =Assumptions!C23 -> 5800 | E20: =Assumptions!C24 -> 11400 | F20: =Assumptions!C25 -> 19800 | G20: =Assumptions!C26 -> 36000
B21: Break-even packs/yr | C21: =C20/C7 -> 9.6551724 | D21: =D20/D7 -> 9.8305085 | E21: =E20/E7 -> 12.808989 | F21: =F20/F7 -> 10.153846 | G21: =G20/G7 -> 14.4
B22: At 8 packs/yr — seat saves | C22: =8*C7-C20 -> -480 | D22: =8*D7-D20 -> -1080 | E22: =8*E7-E20 -> -4280 | F22: =8*F7-F20 -> -4200 | G22: =8*G7-G20 -> -16000
B23: At 12 packs/yr — seat saves | C23: =12*C7-C20 -> 680 | D23: =12*D7-D20 -> 1280 | E23: =12*E7-E20 -> -720 | F23: =12*F7-F20 -> 3600 | G23: =12*G7-G20 -> -6000

Sheet Annual Summary
B2: Annual Summary — Years 1 to 3
B3: Year 1 from monthly cashflow. Years 2-3 ramped on conservative assumptions.
C6: Year 1 (2026-27) | D6: Year 2 (2027-28) | E6: Year 3 (2028-29)
B8: Paying customers (end of year) | C8: ='Monthly Cashflow Y1'!O11 -> 15 | D8: 40 | E8: 85
B9: Annual seats sold (end of year) | C9: 2 | D9: 12 | E9: 32
B11: REVENUE
B12: Per-pack revenue | C12: ='Monthly Cashflow Y1'!O22 -> -285024280 | D12: 85000 | E12: 180000
B13: Annual seat revenue | C13: =C9*Assumptions!C24 -> 22800 | D13: =D9*Assumptions!C24 -> 136800 | E13: =E9*Assumptions!C24 -> 364800
B14: TOTAL REVENUE | C14: =C12+C13 -> -285001480 | D14: =D12+D13 -> 221800 | E14: =E12+E13 -> 544800
B16: COSTS
B17: Direct (compute + honoraria) | C17: =SUM('Monthly Cashflow Y1'!O25:O27) -> -2947.6 | D17: -9500 | E17: -22000
B18: Opex (legal + insurance + mkt + infra) | C18: ='Monthly Cashflow Y1'!O40 -> -12066.667 | D18: -22000 | E18: -42000
B19: Engineering contractor (post-seed) | C19: 0 | D19: -32000 | E19: -65000
B20: TOTAL COSTS | C20: =SUM(C17:C19) -> -15014.267 | D20: =SUM(D17:D19) -> -63500 | E20: =SUM(E17:E19) -> -129000
B22: NET CONTRIBUTION | C22: =C14+C20 -> -2.8501649e+08 | D22: =D14+D20 -> 158300 | E22: =E14+E20 -> 415800
B23: Cumulative | C23: =C22 -> -2.8501649e+08 | D23: =C23+D22 -> -2.8485819e+08 | E23: =D23+E22 -> -2.8444239e+08

Sheet Fundraise Ladder
B2: Fundraise Ladder
B3: Pre-seed → Seed → Series A · gates and triggers.
B6: Round | C6: Timing | D6: Size (€) | E6: Pre-money (€) | F6: Dilution | G6: Gating conditions
B7: Pre-seed (SAFE + EI HPSU) | C7: Month 0-3 | D7: 250000 | E7: 1500000 | F7: 14.3% | G7: SAFE + EI HPSU grant + 1-2 angels. Bridge to seed.
B8: Seed | C8: Month 9 | D8: 2000000 | E8: 8000000 | F8: 20.0% | G8: Gates: 3 paying customers, panel chair signed, POC live, UK reviewer pipeline named.
B9: Series A | C9: Month 24 | D9: 8000000 | E9: 35000000 | F9: 18.6% | G9: Gates: €1m+ ARR, UK launched, 40+ customers, multi-region platform.
B11: Cumulative raised | D11: =SUM(D7:D9) -> 10250000 | F11: ~46% (founder retains ~54%)
B14: USE OF PROCEEDS
B15: Category | C15: Pre-seed (€) | D15: Seed (€) | E15: Series A (€) | F15: Cumulative (€)
B16: Founder salary (post-bootstrap) | C16: 35000 | D16: 110000 | E16: 200000 | F16: =C16+D16+E16 -> 345000
B17: First engineer hire | C17: 0 | D17: 110000 | E17: 220000 | F17: =C17+D17+E17 -> 330000
B18: Sales / partnerships hire | C18: 0 | D18: 75000 | E18: 160000 | F18: =C18+D18+E18 -> 235000
B19: Reviewer panel (full) | C19: 8000 | D19: 75000 | E19: 220000 | F19: =C19+D19+E19 -> 303000
B20: Platform infrastructure | C20: 8000 | D20: 60000 | E20: 180000 | F20: =C20+D20+E20 -> 248000
B21: Marketing + content | C21: 4000 | D21: 80000 | E21: 250000 | F21: =C21+D21+E21 -> 334000
B22: Legal + insurance | C22: 12000 | D22: 50000 | E22: 180000 | F22: =C22+D22+E22 -> 242000
B23: UK market entry | C23: 0 | D23: 250000 | E23: 0 | F23: =C23+D23+E23 -> 250000
B24: AU / CA / EU market entry | C24: 0 | D24: 0 | E24: 1600000 | F24: =C24+D24+E24 -> 1600000
B25: Standards licensing | C25: 0 | D25: 80000 | E25: 220000 | F25: =C25+D25+E25 -> 300000
B26: Working capital + contingency | C26: 33000 | D26: 110000 | E26: 770000 | F26: =C26+D26+E26 -> 913000
B27: TOTAL | C27: =SUM(C16:C26) -> 100000 | D27: =SUM(D16:D26) -> 1000000 | E27: =SUM(E16:E26) -> 4000000 | F27: =SUM(F16:F26) -> 5100000

Sheet Scenarios
B2: Scenarios — Year 1 outcomes
B3: Conservative · Credible · Optimistic. Drives different fundraise narratives.
C6: Conservative | D6: Credible (base) | E6: Optimistic
B7: Paying customers year-end | C7: 8 | D7: 15 | E7: 25
B8: Annual seats year-end | C8: 0 | D8: 2 | E8: 5
B9: Avg packs per customer / year | C9: 4 | D9: 5 | E9: 7
B10: Average tier (1-5) | C10: 2 | D10: 2.4 | E10: 2.8
B11: Free → demo conversion | C11: 0.3 | D11: 0.4 | E11: 0.5
B12: Demo → paid conversion | C12: 0.2 | D12: 0.3 | E12: 0.4
B14: REVENUE — modelled
B15: Per-pack revenue | C15: =C7*C9*(C10*350) -> 22400 | D15: =D7*D9*(D10*350) -> 63000 | E15: =E7*E9*(E10*350) -> 171500
B16: Annual seat revenue (Tier II avg) | C16: =C8*Assumptions!$C$23 -> 0 | D16: =D8*Assumptions!$C$23 -> 11600 | E16: =E8*Assumptions!$C$23 -> 29000
B17: Apply early-pilot 30% (first 10) | C17: =-IF(C7<=10,C15*0.3,C15*0.3*10/C7) -> -6720 | D17: =-IF(D7<=10,D15*0.3,D15*0.3*10/D7) -> -12600 | E17: =-IF(E7<=10,E15*0.3,E15*0.3*10/E7) -> -20580
B18: TOTAL REVENUE | C18: =SUM(C15:C17) -> 15680 | D18: =SUM(D15:D17) -> 62000 | E18: =SUM(E15:E17) -> 179920
