Workbook

Sheet Dashboard
B2: VerifIQ
B3: Token Economics & Pricing Model — Live Working Model
B4: v0.1 — 27-May-2026 — Adjust the YELLOW cells. Everything else recalculates.
B7: Key headline outputs | E7: Sheets in this workbook
B9: Tier 2 (Mid pack) cost per check € | C9: =Pricing!C12 -> 19 | E9: 1. Dashboard — this sheet, headline KPIs
B10: Tier 2 list price € | C10: =Pricing!B12 -> 400 | E10: 2. Inputs — token rates, model prices, market assumptions
B11: Tier 2 gross margin % | C11: =Pricing!E12 -> 0.9525 | E11: 3. Pricing — per-check tier cost, list price, gross margin
B12: Weighted avg gross margin % | C12: =Pricing!E16 -> 0.94427083 | E12: 4. Revenue — Year 1-3 build-up across customer segments
B13: Year-1 revenue at base case € | C13: =Revenue!C12 -> 266400 | E13: 5. Sensitivity — model price flex, customer count flex, margin envelope
B14: Year-1 gross profit € | C14: =Revenue!C20 -> 215470 | E14: 6. Tier Volumes — illustrative pack profiles (drawings, pages, schedules)
B15: Year-3 revenue at base case € | C15: =Revenue!E12 -> 3563632.8
B16: Year-3 gross profit € | C16: =Revenue!E20 -> 3134213.9
B19: Legend
B20: Editable input
B21: Formula / calculated
B22: Key output / KPI

Sheet Inputs
B2: Inputs
B3: Adjust YELLOW cells. All downstream sheets recalculate.
B5: 1. LLM inference rates (€ per 1m tokens)
B7: Frontier model — input tokens | C7: 12 | E7: €/1m tokens. Reference: Claude Sonnet-class input pricing May 2026
B8: Frontier model — output tokens | C8: 50 | E8: €/1m tokens. Reasoning + generation cost
B9: Cheap model — input tokens | C9: 0.8 | E9: €/1m tokens. Used for hygiene / metadata checks
B10: Cheap model — output tokens | C10: 3 | E10: €/1m tokens
B11: % checks using cheap model (smart routing) | C11: 0.4 | E11: Fraction of token volume routed to cheap model
B12: Reasoning multiplier on input tokens | C12: 0.4 | E12: Output tokens as fraction of input (orchestration + findings)
B15: 2. Tier pack profiles (token consumption)
B17: Tier | C17: Description | D17: Input tokens (est.) | E17: List price €
B18: Tier 1 — Small | C18: <50MB / <200 pages | D18: 250000 | E18: 150
B19: Tier 2 — Mid | C19: 50-200MB / 200-600 pages | D19: 950000 | E19: 400
B20: Tier 3 — Large | C20: 200-500MB / 600-1500 pages | D20: 2750000 | E20: 800
B21: Tier 4 — Programme | C21: Multiple packs / month, custom | D21: 5500000 | E21: 1500
B25: 3. Customer segment build (base case, end of Year 1)
B27: Segment | C27: Customers | D27: Avg checks/mo per customer | E27: Avg tier (1/2/3)
B28: Design teams — per-check (Tier 1) | C28: 20 | D28: 1 | E28: 1
B29: Design teams — Practice subscription (Tier 2) | C29: 8 | D29: 1.5 | E29: 2
B30: Design teams — Enterprise subscription (Tier 2-3) | C30: 3 | D30: 2 | E30: 2
B31: Contractors — per-bid (Tier 1-2) | C31: 12 | D31: 1.5 | E31: 2
B32: Employer-side — Programme (Tier 3-4) | C32: 2 | D32: 3 | E32: 3
B35: 4. Year-on-year growth assumptions
B37: Year-2 customer count growth | C37: 2.8 | E37: Multiplier on Year-1 count
B38: Year-3 customer count growth | C38: 2.5 | E38: Multiplier on Year-2 count
B39: Year-2 average usage growth per customer | C39: 1.4 | E39: More checks per customer as they mature
B40: Year-3 average usage growth per customer | C40: 1.3
B41: Year-2 LLM cost reduction | C41: 0.75 | E41: Inference price expected to fall 25%
B42: Year-3 LLM cost reduction | C42: 0.65 | E42: Inference price expected to fall 35% from Year 1

Sheet Pricing
B2: Per-Check Pricing Math
B3: Derived from Inputs sheet. Adjust Inputs to flex these numbers.
A7: Tier | B7: List price € | C7: Cost per check € | D7: Gross profit € | E7: Gross margin %
A11: Tier 1 — Small | B11: =Inputs!E18 -> 150 | C11: =(Inputs!D18/1000000)*((1-Inputs!C11)*Inputs!C7 + Inputs!C11*Inputs!C9)+(Inputs!D18*Inputs!C12/1000000)*((1-Inputs!C11)*Inputs!C8 + Inputs!C11*Inputs!C10) -> 5 | D11: =B11-C11 -> 145 | E11: =IFERROR(D11/B11, 0) -> 0.96666667
A12: Tier 2 — Mid | B12: =Inputs!E19 -> 400 | C12: =(Inputs!D19/1000000)*((1-Inputs!C11)*Inputs!C7 + Inputs!C11*Inputs!C9)+(Inputs!D19*Inputs!C12/1000000)*((1-Inputs!C11)*Inputs!C8 + Inputs!C11*Inputs!C10) -> 19 | D12: =B12-C12 -> 381 | E12: =IFERROR(D12/B12, 0) -> 0.9525
A13: Tier 3 — Large | B13: =Inputs!E20 -> 800 | C13: =(Inputs!D20/1000000)*((1-Inputs!C11)*Inputs!C7 + Inputs!C11*Inputs!C9)+(Inputs!D20*Inputs!C12/1000000)*((1-Inputs!C11)*Inputs!C8 + Inputs!C11*Inputs!C10) -> 55 | D13: =B13-C13 -> 745 | E13: =IFERROR(D13/B13, 0) -> 0.93125
A14: Tier 4 — Programme | B14: =Inputs!E21 -> 1500 | C14: =(Inputs!D21/1000000)*((1-Inputs!C11)*Inputs!C7 + Inputs!C11*Inputs!C9)+(Inputs!D21*Inputs!C12/1000000)*((1-Inputs!C11)*Inputs!C8 + Inputs!C11*Inputs!C10) -> 110 | D14: =B14-C14 -> 1390 | E14: =IFERROR(D14/B14, 0) -> 0.92666667
A16: Weighted avg (assumes equal mix) | B16: =AVERAGE(B11:B14) -> 712.5 | C16: =AVERAGE(C11:C14) -> 47.25 | D16: =AVERAGE(D11:D14) -> 665.25 | E16: =AVERAGE(E11:E14) -> 0.94427083
B19: Margin alert thresholds
B20: Target gross margin floor | C20: 0.75
B21: All tiers above target? | C21: =IF(MIN(E11:E14)>=C20, "YES", "NO") -> YES

Sheet Revenue
B2: Three-Year Revenue & Margin Build-Up
B3: Built from Inputs sheet — segment customer counts × checks × tier price.
A6: Line item | B6: Driver | C6: Year 1 | D6: Year 2 | E6: Year 3
A7: Total customers (end of year) | B7: Sum of segments | C7: =SUM(Inputs!C28:C32) -> 45 | D7: =C7*Inputs!C37 -> 126 | E7: =D7*Inputs!C38 -> 315
A8: Avg checks per customer per year | B8: Weighted by segment | C8: =SUMPRODUCT(Inputs!C28:C32, Inputs!D28:D32)*12/C7 -> 16.533333 | D8: =C8*Inputs!C39 -> 23.146667 | E8: =D8*Inputs!C40 -> 30.090667
A9: Total checks per year | B9: Customers × checks | C9: =C7*C8 -> 744 | D9: =D7*D8 -> 2916.48 | E9: =E7*E8 -> 9478.56
A10: Weighted avg list price € | B10: Segment tier mix | C10: =SUMPRODUCT(Inputs!C28:C32, Inputs!D28:D32, CHOOSE(Inputs!E28:E32, Inputs!E18, Inputs!E19, Inputs!E20, Inputs!E21))/SUMPRODUCT(Inputs!C28:C32, Inputs!D28:D32) -> 358.06452 | D10: =C10 -> 358.06452 | E10: =D10*1.05 -> 375.96774
A12: TOTAL REVENUE | B12: Checks × avg price | C12: =C9*C10 -> 266400 | D12: =D9*D10 -> 1044288 | E12: =E9*E10 -> 3563632.8
A14: Avg cost per check € | B14: Weighted from Pricing sheet | C14: =Pricing!C16 -> 47.25 | D14: =C14*Inputs!C41 -> 35.4375 | E14: =C14*Inputs!C42 -> 30.7125
A15: Total inference cost | B15: Checks × cost | C15: =C9*C14 -> 35154 | D15: =D9*D14 -> 103352.76 | E15: =E9*E14 -> 291110.27
A16: Cloud infra (Convex, hosting, storage) | B16: Fixed + variable | C16: =8000+C9*1.5 -> 9116 | D16: =18000+D9*1.5 -> 22374.72 | E16: =35000+E9*1.5 -> 49217.84
A17: Stripe + payment processing | B17: ~2.5% of revenue | C17: =C12*0.025 -> 6660 | D17: =D12*0.025 -> 26107.2 | E17: =E12*0.025 -> 89090.82
A18: TOTAL COGS | B18: Sum of variable | C18: =SUM(C15:C17) -> 50930 | D18: =SUM(D15:D17) -> 151834.68 | E18: =SUM(E15:E17) -> 429418.93
A20: GROSS PROFIT | B20: Revenue - COGS | C20: =C12-C18 -> 215470 | D20: =D12-D18 -> 892453.32 | E20: =E12-E18 -> 3134213.9
A21: Gross margin % | B21: GP / Revenue | C21: =C20/C12 -> 0.80882132 | D21: =D20/D12 -> 0.85460459 | E21: =E20/E12 -> 0.87949967

Sheet Sensitivity
B2: Sensitivity Analysis
B3: How key outputs flex with input variation.
B5: Tier 2 gross margin at varying frontier model input cost
B7: Frontier input €/1m tokens | C7: Tier 2 cost € | D7: Tier 2 margin %
B8: 4 | C8: =(950000/1000000)*((1-Inputs!C11)*B8+Inputs!C11*Inputs!C9)+(950000*Inputs!C12/1000000)*((1-Inputs!C11)*B8*4.17+Inputs!C11*Inputs!C10) -> 6.84304 | D8: =(Inputs!E19-C8)/Inputs!E19 -> 0.9828924
B9: 8 | C9: =(950000/1000000)*((1-Inputs!C11)*B9+Inputs!C11*Inputs!C9)+(950000*Inputs!C12/1000000)*((1-Inputs!C11)*B9*4.17+Inputs!C11*Inputs!C10) -> 12.92608 | D9: =(Inputs!E19-C9)/Inputs!E19 -> 0.9676848
B10: 12 | C10: =(950000/1000000)*((1-Inputs!C11)*B10+Inputs!C11*Inputs!C9)+(950000*Inputs!C12/1000000)*((1-Inputs!C11)*B10*4.17+Inputs!C11*Inputs!C10) -> 19.00912 | D10: =(Inputs!E19-C10)/Inputs!E19 -> 0.9524772
B11: 18 | C11: =(950000/1000000)*((1-Inputs!C11)*B11+Inputs!C11*Inputs!C9)+(950000*Inputs!C12/1000000)*((1-Inputs!C11)*B11*4.17+Inputs!C11*Inputs!C10) -> 28.13368 | D11: =(Inputs!E19-C11)/Inputs!E19 -> 0.9296658
B12: 24 | C12: =(950000/1000000)*((1-Inputs!C11)*B12+Inputs!C11*Inputs!C9)+(950000*Inputs!C12/1000000)*((1-Inputs!C11)*B12*4.17+Inputs!C11*Inputs!C10) -> 37.25824 | D12: =(Inputs!E19-C12)/Inputs!E19 -> 0.9068544
B13: 36 | C13: =(950000/1000000)*((1-Inputs!C11)*B13+Inputs!C11*Inputs!C9)+(950000*Inputs!C12/1000000)*((1-Inputs!C11)*B13*4.17+Inputs!C11*Inputs!C10) -> 55.50736 | D13: =(Inputs!E19-C13)/Inputs!E19 -> 0.8612316
B16: Year 1 revenue at varying customer counts
B18: Total customers Y1 | C18: Y1 revenue € | D18: Y1 gross profit €
B19: Pessimistic (25) | C19: =Revenue!C12*25/Revenue!C7 -> 148000 | D19: =C19*Revenue!C21 -> 119705.56
B20: Below plan (35) | C20: =Revenue!C12*35/Revenue!C7 -> 207200 | D20: =C20*Revenue!C21 -> 167587.78
B21: Base case (45) | C21: =Revenue!C12*45/Revenue!C7 -> 266400 | D21: =C21*Revenue!C21 -> 215470
B22: Above plan (60) | C22: =Revenue!C12*60/Revenue!C7 -> 355200 | D22: =C22*Revenue!C21 -> 287293.33
B23: Optimistic (85) | C23: =Revenue!C12*85/Revenue!C7 -> 503200 | D23: =C23*Revenue!C21 -> 406998.89

Sheet Tier Volumes
B2: Pack Profile Examples
B3: Token consumption math for the tier definitions. Calibrated against 27 May validation engagement.
B5: Document type | C5: Tokens/page | D5: Tier 1 pages | E5: Tier 1 tokens | F5: Tier 2 pages | G5: Tier 2 tokens | H5: Tier 3 pages | I5: Tier 3 tokens
B6: Drawing register / issue sheet | C6: 4000 | D6: 2 | E6: =C6*D6 -> 8000 | F6: 4 | G6: =C6*F6 -> 16000 | H6: 6 | I6: =C6*H6 -> 24000
B7: Specification body (NBS clause) | C7: 2750 | D7: 120 | E7: =C7*D7 -> 330000 | F7: 380 | G7: =C7*F7 -> 1045000 | H7: 950 | I7: =C7*H7 -> 2612500
B8: GA drawing (vision) | C8: 2250 | D8: 4 | E8: =C8*D8 -> 9000 | F8: 12 | G8: =C8*F8 -> 27000 | H8: 35 | I8: =C8*H8 -> 78750
B9: Detail drawing (vision) | C9: 3500 | D9: 6 | E9: =C9*D9 -> 21000 | F9: 25 | G9: =C9*F9 -> 87500 | H9: 80 | I9: =C9*H9 -> 280000
B10: Schedule sheet (data table) | C10: 5500 | D10: 4 | E10: =C10*D10 -> 22000 | F10: 12 | G10: =C10*F10 -> 66000 | H10: 25 | I10: =C10*H10 -> 137500
B11: Report (Fire B, structural) | C11: 3250 | D11: 4 | E11: =C11*D11 -> 13000 | F11: 18 | G11: =C11*F11 -> 58500 | H11: 40 | I11: =C11*H11 -> 130000
B13: TOTAL | E13: =SUM(E6:E11) -> 403000 | G13: =SUM(G6:G11) -> 1300000 | I13: =SUM(I6:I11) -> 3262750
B15: Calibration vs 27-May-2026 validation engagement
B16: Real pack: 161 PDFs, ~560 pages of spec content, drawings + reports. Token consumption observed: ~1.4m input + ~600k reasoning/output = ~2m total.
B17: Aligned with Tier 2 range (600k-2.2m total) — the May validation engagement was at the upper end of Tier 2.
